[{"id": "K1", "key": "JSON{Doctor\u2019s Name: ?}", "value": "Dr Anup Joshi"}, {"id": "K2", "key": "JSON{Appointment Time: ?}", "value": "Tuesday 15 July 2025, 01:00 PM"}, {"id": "K3", "key": "JSON{Doctor\u2019s Location: ?}", "value": "Om Hospital, Chabahil"}, {"id": "K10", "key": "JSON{Doctor\u2019s Name: ?}", "value": "Dr Anjali Mehta"}, {"id": "K5", "key": "JSON{Appointment Time: ?}", "value": "Friday 04 July 2025, 12:00 PM"}, {"id": "K6", "key": "JSON{Doctor\u2019s Location: ?}", "value": "Grande Hospital, Tokha"}, {"id": "K19", "key": "JSON{Doctor\u2019s Name: ?}", "value": "Dr Milan Gurung"}, {"id": "K8", "key": "JSON{Appointment Time: ?}", "value": "Thursday 03 July 2025, 12:00 PM"}, {"id": "K9", "key": "JSON{Doctor\u2019s Location: ?}", "value": "Grande Hospital, Tokha"}, {"id": "K28", "key": "JSON{Doctor\u2019s Name: ?}", "value": "Dr Rina Shrestha"}, {"id": "K11", "key": "JSON{Appointment Time: ?}", "value": "Thursday 03 July 2025, 09:00 AM"}, {"id": "K12", "key": "JSON{Doctor\u2019s Location: ?}", "value": "Grande Hospital, Tokha"}, {"id": "K37", "key": "JSON{Doctor\u2019s Name: ?}", "value": "Dr Kritika Rai"}, {"id": "K14", "key": "JSON{Appointment Time: ?}", "value": "Friday 25 July 2025, 09:00 AM"}, {"id": "K15", "key": "JSON{Doctor\u2019s Location: ?}", "value": "Sherpa Mall, Durbar Marg"}, {"id": "K46", "key": "JSON{Doctor\u2019s Name: ?}", "value": "Dr Milan Gurung"}, {"id": "K17", "key": "JSON{Appointment Time: ?}", "value": "Thursday 10 July 2025, 09:00 AM"}, {"id": "K18", "key": "JSON{Doctor\u2019s Location: ?}", "value": "Patan Hospital, Lagankhel"}, {"id": "K55", "key": "JSON{Doctor\u2019s Name: ?}", "value": "Dr Anjali Mehta"}, {"id": "K20", "key": "JSON{Appointment Time: ?}", "value": "Thursday 31 July 2025, 11:00 AM"}, {"id": "K21", "key": "JSON{Doctor\u2019s Location: ?}", "value": "Om Hospital, Chabahil"}, {"id": "K64", "key": "JSON{Doctor\u2019s Name: ?}", "value": "Dr Rupesh Sharma"}, {"id": "K23", "key": "JSON{Appointment Time: ?}", "value": "Saturday 12 July 2025, 01:00 PM"}, {"id": "K24", "key": "JSON{Doctor\u2019s Location: ?}", "value": "B&B Hospital, Gwarko"}, {"id": "K73", "key": "JSON{Doctor\u2019s Name: ?}", "value": "Dr Rina Shrestha"}, {"id": "K26", "key": "JSON{Appointment Time: ?}", "value": "Tuesday 08 July 2025, 09:00 AM"}, {"id": "K27", "key": "JSON{Doctor\u2019s Location: ?}", "value": "Alka Hospital, Lalitpur"}, {"id": "K82", "key": "JSON{Doctor\u2019s Name: ?}", "value": "Dr Rina Shrestha"}, {"id": "K29", "key": "JSON{Appointment Time: ?}", "value": "Sunday 27 July 2025, 01:00 PM"}, {"id": "K30", "key": "JSON{Doctor\u2019s Location: ?}", "value": "Norvic Hospital, Thapathali"}, {"id": "K91", "key": "JSON{Doctor\u2019s Name: ?}", "value": "Dr Milan Gurung"}, {"id": "K32", "key": "JSON{Appointment Time: ?}", "value": "Monday 14 July 2025, 09:00 AM"}, {"id": "K33", "key": "JSON{Doctor\u2019s Location: ?}", "value": "Grande Hospital, Tokha"}, {"id": "K100", "key": "JSON{Doctor\u2019s Name: ?}", "value": "Dr Milan Gurung"}, {"id": "K35", "key": "JSON{Appointment Time: ?}", "value": "Friday 18 July 2025, 10:00 AM"}, {"id": "K36", "key": "JSON{Doctor\u2019s Location: ?}", "value": "Alka Hospital, Lalitpur"}, {"id": "K109", "key": "JSON{Doctor\u2019s Name: ?}", "value": "Dr Anup Joshi"}, {"id": "K38", "key": "JSON{Appointment Time: ?}", "value": "Saturday 19 July 2025, 11:00 AM"}, {"id": "K39", "key": "JSON{Doctor\u2019s Location: ?}", "value": "Om Hospital, Chabahil"}, {"id": "K118", "key": "JSON{Doctor\u2019s Name: ?}", "value": "Dr Sunil Adhikari"}, {"id": "K41", "key": "JSON{Appointment Time: ?}", "value": "Sunday 13 July 2025, 11:00 AM"}, {"id": "K42", "key": "JSON{Doctor\u2019s Location: ?}", "value": "Patan Hospital, Lagankhel"}, {"id": "K127", "key": "JSON{Doctor\u2019s Name: ?}", "value": "Dr Kritika Rai"}, {"id": "K44", "key": "JSON{Appointment Time: ?}", "value": "Tuesday 01 July 2025, 01:00 PM"}, {"id": "K45", "key": "JSON{Doctor\u2019s Location: ?}", "value": "B&B Hospital, Gwarko"}, {"id": "K136", "key": "JSON{Doctor\u2019s Name: ?}", "value": "Dr Prakash Ghimire"}, {"id": "K47", "key": "JSON{Appointment Time: ?}", "value": "Friday 25 July 2025, 09:00 AM"}, {"id": "K48", "key": "JSON{Doctor\u2019s Location: ?}", "value": "Grande Hospital, Tokha"}, {"id": "K145", "key": "JSON{Doctor\u2019s Name: ?}", "value": "Dr Kritika Rai"}, {"id": "K50", "key": "JSON{Appointment Time: ?}", "value": "Saturday 12 July 2025, 11:00 AM"}, {"id": "K51", "key": "JSON{Doctor\u2019s Location: ?}", "value": "Teaching Hospital, Maharajgunj"}, {"id": "K154", "key": "JSON{Doctor\u2019s Name: ?}", "value": "Dr Anjali Mehta"}, {"id": "K53", "key": "JSON{Appointment Time: ?}", "value": "Sunday 13 July 2025, 12:00 PM"}, {"id": "K54", "key": "JSON{Doctor\u2019s Location: ?}", "value": "Om Hospital, Chabahil"}, {"id": "K163", "key": "JSON{Doctor\u2019s Name: ?}", "value": "Dr Anjali Mehta"}, {"id": "K56", "key": "JSON{Appointment Time: ?}", "value": "Thursday 10 July 2025, 10:00 AM"}, {"id": "K57", "key": "JSON{Doctor\u2019s Location: ?}", "value": "Medicare Hospital, Chabahil"}, {"id": "K172", "key": "JSON{Doctor\u2019s Name: ?}", "value": "Dr Rupesh Sharma"}, {"id": "K59", "key": "JSON{Appointment Time: ?}", "value": "Friday 11 July 2025, 11:00 AM"}, {"id": "K60", "key": "JSON{Doctor\u2019s Location: ?}", "value": "Teaching Hospital, Maharajgunj"}, {"id": "K181", "key": "JSON{Doctor\u2019s Name: ?}", "value": "Dr Suresh Thapa"}, {"id": "K62", "key": "JSON{Appointment Time: ?}", "value": "Tuesday 29 July 2025, 10:00 AM"}, {"id": "K63", "key": "JSON{Doctor\u2019s Location: ?}", "value": "Grande Hospital, Tokha"}, {"id": "K190", "key": "JSON{Doctor\u2019s Name: ?}", "value": "Dr Anjali Mehta"}, {"id": "K65", "key": "JSON{Appointment Time: ?}", "value": "Thursday 24 July 2025, 09:00 AM"}, {"id": "K66", "key": "JSON{Doctor\u2019s Location: ?}", "value": "Sherpa Mall, Durbar Marg"}, {"id": "K199", "key": "JSON{Doctor\u2019s Name: ?}", "value": "Dr Anup Joshi"}, {"id": "K68", "key": "JSON{Appointment Time: ?}", "value": "Wednesday 30 July 2025, 11:00 AM"}, {"id": "K69", "key": "JSON{Doctor\u2019s Location: ?}", "value": "Teaching Hospital, Maharajgunj"}, {"id": "K208", "key": "JSON{Doctor\u2019s Name: ?}", "value": "Dr Kritika Rai"}, {"id": "K71", "key": "JSON{Appointment Time: ?}", "value": "Wednesday 30 July 2025, 01:00 PM"}, {"id": "K72", "key": "JSON{Doctor\u2019s Location: ?}", "value": "Patan Hospital, Lagankhel"}, {"id": "K217", "key": "JSON{Doctor\u2019s Name: ?}", "value": "Dr Rupesh Sharma"}, {"id": "K74", "key": "JSON{Appointment Time: ?}", "value": "Tuesday 15 July 2025, 09:00 AM"}, {"id": "K75", "key": "JSON{Doctor\u2019s Location: ?}", "value": "Grande Hospital, Tokha"}, {"id": "K226", "key": "JSON{Doctor\u2019s Name: ?}", "value": "Dr Prakash Ghimire"}, {"id": "K77", "key": "JSON{Appointment Time: ?}", "value": "Sunday 20 July 2025, 11:00 AM"}, {"id": "K78", "key": "JSON{Doctor\u2019s Location: ?}", "value": "B&B Hospital, Gwarko"}, {"id": "K235", "key": "JSON{Doctor\u2019s Name: ?}", "value": "Dr Nirmala Karki"}, {"id": "K80", "key": "JSON{Appointment Time: ?}", "value": "Tuesday 29 July 2025, 10:00 AM"}, {"id": "K81", "key": "JSON{Doctor\u2019s Location: ?}", "value": "Medicare Hospital, Chabahil"}, {"id": "K244", "key": "JSON{Doctor\u2019s Name: ?}", "value": "Dr Anup Joshi"}, {"id": "K83", "key": "JSON{Appointment Time: ?}", "value": "Tuesday 29 July 2025, 09:00 AM"}, {"id": "K84", "key": "JSON{Doctor\u2019s Location: ?}", "value": "Om Hospital, Chabahil"}, {"id": "K253", "key": "JSON{Doctor\u2019s Name: ?}", "value": "Dr Nirmala Karki"}, {"id": "K86", "key": "JSON{Appointment Time: ?}", "value": "Thursday 03 July 2025, 09:00 AM"}, {"id": "K87", "key": "JSON{Doctor\u2019s Location: ?}", "value": "Vayodha Hospital, Balkhu"}, {"id": "K262", "key": "JSON{Doctor\u2019s Name: ?}", "value": "Dr Rina Shrestha"}, {"id": "K89", "key": "JSON{Appointment Time: ?}", "value": "Tuesday 08 July 2025, 11:00 AM"}, {"id": "K90", "key": "JSON{Doctor\u2019s Location: ?}", "value": "Teaching Hospital, Maharajgunj"}, {"id": "K271", "key": "JSON{Doctor\u2019s Name: ?}", "value": "Dr Milan Gurung"}, {"id": "K92", "key": "JSON{Appointment Time: ?}", "value": "Wednesday 09 July 2025, 12:00 PM"}, {"id": "K93", "key": "JSON{Doctor\u2019s Location: ?}", "value": "Norvic Hospital, Thapathali"}, {"id": "K280", "key": "JSON{Doctor\u2019s Name: ?}", "value": "Dr Prakash Ghimire"}, {"id": "K95", "key": "JSON{Appointment Time: ?}", "value": "Wednesday 30 July 2025, 11:00 AM"}, {"id": "K96", "key": "JSON{Doctor\u2019s Location: ?}", "value": "Norvic Hospital, Thapathali"}, {"id": "K289", "key": "JSON{Doctor\u2019s Name: ?}", "value": "Dr Anup Joshi"}, {"id": "K98", "key": "JSON{Appointment Time: ?}", "value": "Saturday 19 July 2025, 01:00 PM"}, {"id": "K99", "key": "JSON{Doctor\u2019s Location: ?}", "value": "Patan Hospital, Lagankhel"}, {"id": "K298", "key": "JSON{Doctor\u2019s Name: ?}", "value": "Dr Rupesh Sharma"}, {"id": "K101", "key": "JSON{Appointment Time: ?}", "value": "Friday 11 July 2025, 10:00 AM"}, {"id": "K102", "key": "JSON{Doctor\u2019s Location: ?}", "value": "Norvic Hospital, Thapathali"}, {"id": "K307", "key": "JSON{Doctor\u2019s Name: ?}", "value": "Dr Anjali Mehta"}, {"id": "K104", "key": "JSON{Appointment Time: ?}", "value": "Thursday 03 July 2025, 10:00 AM"}, {"id": "K105", "key": "JSON{Doctor\u2019s Location: ?}", "value": "Norvic Hospital, Thapathali"}, {"id": "K316", "key": "JSON{Doctor\u2019s Name: ?}", "value": "Dr Rina Shrestha"}, {"id": "K107", "key": "JSON{Appointment Time: ?}", "value": "Thursday 17 July 2025, 10:00 AM"}, {"id": "K108", "key": "JSON{Doctor\u2019s Location: ?}", "value": "Sherpa Mall, Durbar Marg"}, {"id": "K325", "key": "JSON{Doctor\u2019s Name: ?}", "value": "Dr Nirmala Karki"}, {"id": "K110", "key": "JSON{Appointment Time: ?}", "value": "Thursday 10 July 2025, 11:00 AM"}, {"id": "K111", "key": "JSON{Doctor\u2019s Location: ?}", "value": "Alka Hospital, Lalitpur"}, {"id": "K334", "key": "JSON{Doctor\u2019s Name: ?}", "value": "Dr Anup Joshi"}, {"id": "K113", "key": "JSON{Appointment Time: ?}", "value": "Sunday 06 July 2025, 09:00 AM"}, {"id": "K114", "key": "JSON{Doctor\u2019s Location: ?}", "value": "Teaching Hospital, Maharajgunj"}, {"id": "K343", "key": "JSON{Doctor\u2019s Name: ?}", "value": "Dr Anjali Mehta"}, {"id": "K116", "key": "JSON{Appointment Time: ?}", "value": "Monday 21 July 2025, 10:00 AM"}, {"id": "K117", "key": "JSON{Doctor\u2019s Location: ?}", "value": "Sherpa Mall, Durbar Marg"}, {"id": "K352", "key": "JSON{Doctor\u2019s Name: ?}", "value": "Dr Prakash Ghimire"}, {"id": "K119", "key": "JSON{Appointment Time: ?}", "value": "Sunday 20 July 2025, 01:00 PM"}, {"id": "K120", "key": "JSON{Doctor\u2019s Location: ?}", "value": "Alka Hospital, Lalitpur"}, {"id": "K361", "key": "JSON{Doctor\u2019s Name: ?}", "value": "Dr Kritika Rai"}, {"id": "K122", "key": "JSON{Appointment Time: ?}", "value": "Monday 28 July 2025, 01:00 PM"}, {"id": "K123", "key": "JSON{Doctor\u2019s Location: ?}", "value": "Patan Hospital, Lagankhel"}, {"id": "K370", "key": "JSON{Doctor\u2019s Name: ?}", "value": "Dr Rina Shrestha"}, {"id": "K125", "key": "JSON{Appointment Time: ?}", "value": "Sunday 13 July 2025, 11:00 AM"}, {"id": "K126", "key": "JSON{Doctor\u2019s Location: ?}", "value": "Sherpa Mall, Durbar Marg"}, {"id": "K379", "key": "JSON{Doctor\u2019s Name: ?}", "value": "Dr Rupesh Sharma"}, {"id": "K128", "key": "JSON{Appointment Time: ?}", "value": "Wednesday 30 July 2025, 10:00 AM"}, {"id": "K129", "key": "JSON{Doctor\u2019s Location: ?}", "value": "Alka Hospital, Lalitpur"}, {"id": "K388", "key": "JSON{Doctor\u2019s Name: ?}", "value": "Dr Milan Gurung"}, {"id": "K131", "key": "JSON{Appointment Time: ?}", "value": "Sunday 13 July 2025, 09:00 AM"}, {"id": "K132", "key": "JSON{Doctor\u2019s Location: ?}", "value": "Om Hospital, Chabahil"}, {"id": "K397", "key": "JSON{Doctor\u2019s Name: ?}", "value": "Dr Rupesh Sharma"}, {"id": "K134", "key": "JSON{Appointment Time: ?}", "value": "Monday 21 July 2025, 09:00 AM"}, {"id": "K135", "key": "JSON{Doctor\u2019s Location: ?}", "value": "Alka Hospital, Lalitpur"}, {"id": "K406", "key": "JSON{Doctor\u2019s Name: ?}", "value": "Dr Sunil Adhikari"}, {"id": "K137", "key": "JSON{Appointment Time: ?}", "value": "Monday 28 July 2025, 10:00 AM"}, {"id": "K138", "key": "JSON{Doctor\u2019s Location: ?}", "value": "Om Hospital, Chabahil"}, {"id": "K415", "key": "JSON{Doctor\u2019s Name: ?}", "value": "Dr Prakash Ghimire"}, {"id": "K140", "key": "JSON{Appointment Time: ?}", "value": "Friday 04 July 2025, 12:00 PM"}, {"id": "K141", "key": "JSON{Doctor\u2019s Location: ?}", "value": "Medicare Hospital, Chabahil"}, {"id": "K424", "key": "JSON{Doctor\u2019s Name: ?}", "value": "Dr Anjali Mehta"}, {"id": "K143", "key": "JSON{Appointment Time: ?}", "value": "Wednesday 23 July 2025, 10:00 AM"}, {"id": "K144", "key": "JSON{Doctor\u2019s Location: ?}", "value": "Norvic Hospital, Thapathali"}, {"id": "K433", "key": "JSON{Doctor\u2019s Name: ?}", "value": "Dr Rina Shrestha"}, {"id": "K146", "key": "JSON{Appointment Time: ?}", "value": "Thursday 17 July 2025, 11:00 AM"}, {"id": "K147", "key": "JSON{Doctor\u2019s Location: ?}", "value": "Alka Hospital, Lalitpur"}, {"id": "K442", "key": "JSON{Doctor\u2019s Name: ?}", "value": "Dr Anjali Mehta"}, {"id": "K149", "key": "JSON{Appointment Time: ?}", "value": "Wednesday 30 July 2025, 12:00 PM"}, {"id": "K150", "key": "JSON{Doctor\u2019s Location: ?}", "value": "Medicare Hospital, Chabahil"}]